{
    "switches": 1,
    "max time": 9999999,
    "default input gap": 100,
    "random seed": 0,
    "python file": "rtt.py",
    "events": [
        {
            "name": "tcp_in",
            "args": [
                24,
                108,
                5,
                5,
                389537286,
                3974322786,
                4093882517,
                699466720,
                1869,
                9809,
                5524034
            ]
        },
        {
            "name": "tcp_in",
            "args": [
                16,
                40,
                5,
                5,
                3974322862,
                389537355,
                699466720,
                4093882517,
                9809,
                1869,
                6418034
            ]
        }
    ]
}
